MANIFEST.in
README.md
setup.cfg
setup.py
coreapidr/__init__.py
coreapidr/auth.py
coreapidr/client.py
coreapidr/compat.py
coreapidr/document.py
coreapidr/exceptions.py
coreapidr/utils.py
coreapidr.egg-info/PKG-INFO
coreapidr.egg-info/SOURCES.txt
coreapidr.egg-info/dependency_links.txt
coreapidr.egg-info/entry_points.txt
coreapidr.egg-info/requires.txt
coreapidr.egg-info/top_level.txt
coreapidr/codecs/__init__.py
coreapidr/codecs/base.py
coreapidr/codecs/corejson.py
coreapidr/codecs/display.py
coreapidr/codecs/download.py
coreapidr/codecs/jsondata.py
coreapidr/codecs/python.py
coreapidr/codecs/text.py
coreapidr/transports/__init__.py
coreapidr/transports/base.py
coreapidr/transports/http.py